speedtest/__init__.py
speedtest/speedtest.py
speedtest_personal-2.0.dist-info/LICENSE.txt
speedtest_personal-2.0.dist-info/METADATA
speedtest_personal-2.0.dist-info/WHEEL
speedtest_personal-2.0.dist-info/top_level.txt
speedtest_personal-2.0.dist-info/RECORD
