Metadata-Version: 2.1
Name: speedtest-personal
Version: 2.0
Summary: A direct fork of speedtest-cli. Please use the original package as this is just for my personal use.
Home-page: https://github.com/Aagam41/speedtest
Author: Aagam Sheth
Author-email: aagam.h.sheth@icloud.com
License: MIT
Download-URL: https://github.com/Aagam41/speedtest/archive/v_01.tar.gz
Platform: UNKNOWN
Classifier: Intended Audience :: Developers
Classifier: Topic :: Software Development :: Build Tools
Classifier: License :: OSI Approved :: MIT License
Classifier: Programming Language :: Python :: 3
Classifier: Programming Language :: Python :: 3.4
Classifier: Programming Language :: Python :: 3.5
Classifier: Programming Language :: Python :: 3.6
